audio_devices/__init__.py
audio_devices/_audio_devices.cp310-win_amd64.pyd
audio_devices/_audio_devices.cpp
audio_devices-0.2.0.dist-info/licenses/LICENSE
audio_devices-0.2.0.dist-info/METADATA
audio_devices-0.2.0.dist-info/WHEEL
audio_devices-0.2.0.dist-info/top_level.txt
audio_devices-0.2.0.dist-info/RECORD
