Metadata-Version: 2.4
Name: audio_devices
Version: 0.2.0
Summary: Cross-platform audio device enumeration library
Author-email: nohanaga <your.email@example.com>
License: MIT
Project-URL: Homepage, https://github.com/nohanaga/audio_devices
Project-URL: Repository, https://github.com/nohanaga/audio_devices
Project-URL: Issues, https://github.com/nohanaga/audio_devices/issues
Project-URL: Documentation, https://github.com/nohanaga/audio_devices#readme
Keywords: audio,devices,sound,multimedia,cross-platform
Classifier: Development Status :: 4 - Beta
Classifier: Intended Audience :: Developers
Classifier: License :: OSI Approved :: MIT License
Classifier: Operating System :: OS Independent
Classifier: Programming Language :: Python :: 3
Classifier: Programming Language :: Python :: 3.8
Classifier: Programming Language :: Python :: 3.9
Classifier: Programming Language :: Python :: 3.10
Classifier: Programming Language :: Python :: 3.11
Classifier: Programming Language :: Python :: 3.12
Classifier: Topic :: Multimedia :: Sound/Audio
Classifier: Topic :: System :: Hardware
Requires-Python: >=3.8
License-File: LICENSE
Dynamic: license-file
